setup.py
Bgp.egg-info/PKG-INFO
Bgp.egg-info/SOURCES.txt
Bgp.egg-info/dependency_links.txt
Bgp.egg-info/requires.txt
Bgp.egg-info/top_level.txt
bgp/__init__.py
bgp/bgplib.py
bgp/userBgp.py
bgp/vlan1001.cfg