Metadata-Version: 1.0
Name: Bgp
Version: 0.2
Summary: test tool bgp
Home-page: http://github.com/sudks/bgp
Author: Sudarshana K S
Author-email: sudarshana.ks@gmail.com
License: UNKNOWN
Keywords: tcp,bgp,scapy,network,dissect,packets
Platform: any
